pymqttlights/__init__.py
pymqttlights/config.py
pymqttlights/pymqttlights.py
pymqttlights/utils.py
pymqttlights-1.0.0.dist-info/METADATA
pymqttlights-1.0.0.dist-info/WHEEL
pymqttlights-1.0.0.dist-info/top_level.txt
pymqttlights-1.0.0.dist-info/RECORD
