Metadata-Version: 2.1
Name: pymqttlights
Version: 1.0.0
Summary: Simple python library to control custom MQTT based fairylights
Home-page: https://github.com/fedus
Author: Federico Gentile
Author-email: misc+pypi@dillendapp.eu
License: MIT
Platform: UNKNOWN
Classifier: License :: OSI Approved :: MIT License
Classifier: Programming Language :: Python :: 3
Classifier: Programming Language :: Python :: 3.7
Requires-Dist: paho-mqtt
